ice_pick/__init__.py
ice_pick/account_object.py
ice_pick/extension.py
ice_pick/filters.py
ice_pick/privileges.py
ice_pick/schema_object.py
ice_pick/utils.py
ice_pick/version.py
snowflake_ice_pick-0.0.6.dist-info/LICENSE
snowflake_ice_pick-0.0.6.dist-info/METADATA
snowflake_ice_pick-0.0.6.dist-info/WHEEL
snowflake_ice_pick-0.0.6.dist-info/top_level.txt
snowflake_ice_pick-0.0.6.dist-info/RECORD
