Metadata-Version: 2.1
Name: snowflake_ice_pick
Version: 0.0.6
Summary: Snowpark extension to cover additional objects and higher level functions
Author: Preston Blackburn
License: The MIT License (MIT)
Project-URL: Homepage, https://github.com/PrestonBlackburn/ice_pick
Keywords: snowflake,metadata,utils
Classifier: License :: OSI Approved :: MIT License
Classifier: Programming Language :: Python
Classifier: Programming Language :: Python :: 3
Classifier: Development Status :: 1 - Planning
Classifier: Topic :: Software Development :: Libraries
Classifier: Topic :: Utilities
Requires-Python: >=3.8.0
License-File: LICENSE
Requires-Dist: pandas
Requires-Dist: snowflake-snowpark-python
Requires-Dist: setuptools
Requires-Dist: wheel
Requires-Dist: cloudpickle
Provides-Extra: doc
Requires-Dist: sphinx ; extra == 'doc'
Requires-Dist: myst-parser ; extra == 'doc'
Requires-Dist: furo ; extra == 'doc'
Requires-Dist: nbsphinx ; extra == 'doc'
Requires-Dist: ipykernel ; extra == 'doc'
Requires-Dist: IPython ; extra == 'doc'
